{
    "Item":[
        {
            "Vanilla":true,
            "ID":"Skeleton Head"
        }
    ],
    "Display_Name":"<orange>Skeleton {@traitless}",
    "PetID":"Skeleton",
    "Rarity":5,
    "Class":"Pet",
    "Type":"Pet",
    "Traits": ["Traitless"],
    "Stats": [
        {
            "CC":5
        }
    ],
    "AbilityCount":3,
    "Abilities": [
        {
            "ID":"Bone_Plating",
            "Trigger":0,
            "Description": [
                "&6Pet Ability: Bone Plating &e&lPASSIVE", 
                "Your skeleton pet's thick bone plating",
                "reduces the damage you take from",
                "most types of arrows by &a25%"
                
            ]
        },
        {
            "ID":"Bone_Toss",
            "AbilityName":"Deadly Bone",
            "Trigger":2,
            "Damage":500,
            "Cooldown":30, 
            "Mana_Cost":100,
            "Soul_Cost":1,
            "Intelligence_Scaling":0.4,
            "Description": [
                "&6Pet Ability: Deadly Bone &e&lRIGHT CLICK", 
                "Throw a very heavy bone projectile,",
                "dealing &c{Damage} &cDamage &7on hit.",
                "&ePiercing {@Piercing}",
                "&cMassive Damage {@Massive_Damage} &cto &aNature {@nature}"
            ],
            "Effects":"Massive_Damage-Nature" 
        },
        {
            "ID":"Headshot",
            "Trigger":0,
            "Description": [
                "&6Pet Ability: Headshot &e&lPASSIVE", 
                "Arrows and &eDeadly Bone &7get a",
                "&a20% &7damage bonus from landing",
                "a &cHeadshot"
            ]
        }  
    ],
    "isReforgeable":false,
    "Glow":false,
    "Combat":3
}
